api/__init__.py
api/v1/__init__.py
api/v1/clash.py
api/v1/redis.py
cli/__init__.py
cli/baidu.py
cli/bitget.py
cli/example.py
cli/fast.py
cli/gate.py
cli/redis_csv.py
cli/util.py
core/__init__.py
core/clash.py
core/config.py
core/redis_client.py
crypto/__init__.py
crypto/bitget.py
crypto/gate.py
data/__init__.py
data/dou_dict.py
data/dou_list.py
data/main.py
data/template.yaml
models/__init__.py
models/douzero_model.py
models/ocr_model.py
models/response.py
utils/__init__.py
utils/elapsed.py
utils/helper.py
utils/logger.py
utils/mysql.py
utils/path.py
utils/pd.py
utils/pyredis.py
utils/sleep.py
utils/text.py
utils/toml.py
pymecli-0.3.2.dist-info/METADATA
pymecli-0.3.2.dist-info/WHEEL
pymecli-0.3.2.dist-info/entry_points.txt
pymecli-0.3.2.dist-info/RECORD
