Metadata-Version: 2.4
Name: pymecli
Version: 0.3.2
Summary: My CLI
Project-URL: Homepage, https://pypi.org/project/pymecli
Project-URL: Repository, https://github.com/meme2046/pymecli
License: MIT
Classifier: Intended Audience :: Developers
Classifier: License :: OSI Approved :: MIT License
Classifier: Programming Language :: Python :: 3
Requires-Python: >=3.10
Requires-Dist: arrow>=1.4.0
Requires-Dist: babel>=2.17.0
Requires-Dist: cowsay>=6.1
Requires-Dist: dotenv>=0.9.9
Requires-Dist: fastapi>=0.127.0
Requires-Dist: numpy<2.0.0
Requires-Dist: pandas>=2.3.3
Requires-Dist: pymysql>=1.1.2
Requires-Dist: pytz>=2025.2
Requires-Dist: pyyaml>=6.0.3
Requires-Dist: redis[hiredis]>=7.1.0
Requires-Dist: requests[socks]>=2.32.5
Requires-Dist: selenium>=4.40.0
Requires-Dist: sqlalchemy>=2.0.45
Requires-Dist: tabulate>=0.9.0
Requires-Dist: toml>=0.10.2
Requires-Dist: typer>=0.20.1
Requires-Dist: uvicorn>=0.40.0
Requires-Dist: webdriver-manager>=4.0.2
